tests/__init__.py
tests/test_gee.py
tests/test_main.py
tests/test_watershed.py
waterpyk/__init__.py
waterpyk/calcs.py
waterpyk/errors.py
waterpyk/gee.py
waterpyk/main.py
waterpyk/mapping_tools.py
waterpyk/plots.py
waterpyk/raster.py
waterpyk/shapefile.py
waterpyk/watershed.py
waterpyk/layers_data/all.csv
waterpyk/layers_data/minimal.csv
waterpyk-2.3.0.dist-info/LICENSE
waterpyk-2.3.0.dist-info/METADATA
waterpyk-2.3.0.dist-info/WHEEL
waterpyk-2.3.0.dist-info/top_level.txt
waterpyk-2.3.0.dist-info/RECORD
