Metadata-Version: 2.1
Name: waterpyk
Version: 2.3.0
Summary: Extract, analyze, and plot hydrological timeseries for a site or watershed using the Google Earth Engine and USGS APIs
Home-page: https://github.com/erica-mccormick/waterpyk
Author: Erica L. McCormick
Author-email: erica.elmstead@gmail.com
License: MIT
Classifier: Programming Language :: Python :: 3
Classifier: Programming Language :: Python :: 3.7
Classifier: Intended Audience :: Science/Research
Classifier: Natural Language :: English
Classifier: Topic :: Scientific/Engineering :: GIS
Classifier: Development Status :: 4 - Beta
License-File: LICENSE
